{"url": "/greninja", "date": "2022-09-19 15:00:40.528153", "moves": {"jab_1": {"hitbox": "hitboxes/greninja/GreninjaJab1.gif", "movename": "Jab 1", "startup": "3", "totalframes": "21", "landinglag": "--", "notes": "Transitions to jab 2 as early as frame 6", "basedamage": "2.0", "shieldlag": "8", "shieldstun": "3", "whichhitbox": "--", "advantage": "-15", "activeframes": "3"}, "jab_2": {"hitbox": "hitboxes/greninja/GreninjaJab2.gif", "movename": "Jab 2", "startup": "3", "totalframes": "21", "landinglag": "--", "notes": "Transitions to jab 3 as early as frame 6", "basedamage": "2.0", "shieldlag": "5", "shieldstun": "3", "whichhitbox": "--", "advantage": "-15", "activeframes": "3\u20144"}, "jab_3": {"hitbox": "hitboxes/greninja/GreninjaJab3.gif", "movename": "Jab 3", "startup": "5", "totalframes": "35", "landinglag": "--", "notes": "--", "basedamage": "3.0", "shieldlag": "10", "shieldstun": "4", "whichhitbox": "--", "advantage": "-26", "activeframes": "5\u20146"}, "rapid_jab": {"hitbox": "hitboxes/greninja/GreninjaJabRapid.gif", "movename": "Rapid Jab", "startup": "5/8/11/14...", "totalframes": "**", "landinglag": "--", "notes": "--", "basedamage": "0.5", "shieldlag": "4", "shieldstun": "3", "whichhitbox": "--", "advantage": "--", "activeframes": "**"}, "rapid_jab_finisher": {"hitbox": "hitboxes/greninja/GreninjaJabRapidEnd.gif", "movename": "Rapid Jab Finisher", "startup": "4", "totalframes": "47", "landinglag": "--", "notes": "--", "basedamage": "2.0", "shieldlag": "9", "shieldstun": "3", "whichhitbox": "--", "advantage": "-39", "activeframes": "4\u20145"}, "forward_tilt": {"hitbox": "hitboxes/greninja/GreninjaFTilt.gif", "movename": "Forward Tilt", "startup": "10", "totalframes": "32", "landinglag": "--", "notes": "--", "basedamage": "7.3/8.3", "shieldlag": "7/7", "shieldstun": "7/8", "whichhitbox": "No Angle/Angled", "advantage": "-15/-14", "activeframes": "10\u201412"}, "up_tilt": {"hitbox": "hitboxes/greninja/GreninjaUTilt.gif", "movename": "Up Tilt", "startup": "9", "totalframes": "32", "landinglag": "--", "notes": "--", "basedamage": "4.5", "shieldlag": "5", "shieldstun": "5", "whichhitbox": "--", "advantage": "-18", "activeframes": "9\u201412"}, "down_tilt": {"hitbox": "hitboxes/greninja/GreninjaDTilt.gif", "movename": "Down Tilt", "startup": "5", "totalframes": "22", "landinglag": "--", "notes": "--", "basedamage": "4.0", "shieldlag": "5", "shieldstun": "5", "whichhitbox": "--", "advantage": "-12", "activeframes": "5\u20146"}, "dash_attack": {"hitbox": "hitboxes/greninja/GreninjaDashAttack.gif", "movename": "Dash Attack", "startup": "7", "totalframes": "28", "landinglag": "--", "notes": "--", "basedamage": "8.0", "shieldlag": "7", "shieldstun": "8", "whichhitbox": "--", "advantage": "-13", "activeframes": "7\u201411"}, "forward_smash": {"hitbox": "hitboxes/greninja/GreninjaFSmash.gif", "movename": "Forward Smash", "startup": "13", "totalframes": "49", "landinglag": "--", "notes": "Charge hold is frame 7", "basedamage": "14.0", "shieldlag": "10", "shieldstun": "10", "whichhitbox": "--", "advantage": "-26", "activeframes": "13\u201415"}, "up_smash": {"hitbox": "hitboxes/greninja/GreninjaUSmash.gif", "movename": "Up Smash", "startup": "12/18", "totalframes": "51", "landinglag": "--", "notes": "Charge hold is frame 8", "basedamage": "5.0/14.0/11.0", "shieldlag": "8/14/8", "shieldstun": "4/10/8", "whichhitbox": "First/Second/Late", "advantage": "-23", "activeframes": "12\u201417/18(19\u201420/21)"}, "down_smash": {"hitbox": "hitboxes/greninja/GreninjaDSmash.gif", "movename": "Down Smash", "startup": "11", "totalframes": "49", "landinglag": "--", "notes": "Charge hold is frame 4", "basedamage": "13.0/11.0", "shieldlag": "9/?", "shieldstun": "9/?", "whichhitbox": "Far/Close", "advantage": "-29", "activeframes": "11\u201412(13)"}, "down_taunt": {"hitbox": "hitboxes/greninja/GreninjaDTaunt.gif", "movename": "Down Taunt", "startup": "30", "totalframes": "79", "landinglag": "--", "notes": "Does not give aerial opponents hit stun", "basedamage": "0.5", "shieldlag": "**", "shieldstun": "**", "whichhitbox": "--", "advantage": "**", "activeframes": "30\u201473 (rehit: 3)"}, "neutral_air": {"hitbox": "hitboxes/greninja/GreninjaNAir.gif", "movename": "Neutral Air", "startup": "12", "totalframes": "52", "landinglag": "7", "notes": "Autocancels on frame 1-9 and 40 onward", "basedamage": "11.0/6.0", "shieldlag": "8/6", "shieldstun": "4/3", "whichhitbox": "--", "advantage": "-3/-4", "activeframes": "12\u201413(14\u201419)"}, "forward_air": {"hitbox": "hitboxes/greninja/GreninjaFAir.gif", "movename": "Forward Air", "startup": "16", "totalframes": "54", "landinglag": "11", "notes": "Autocancels on frame 1-12 and 40 onward", "basedamage": "14.0", "shieldlag": "11", "shieldstun": "5", "whichhitbox": "--", "advantage": "-6", "activeframes": "16\u201417"}, "back_air": {"hitbox": "hitboxes/greninja/GreninjaBAir.gif", "movename": "Back Air", "startup": "5/7/11", "totalframes": "40", "landinglag": "10", "notes": "Autocancels on frame 1-3 and 35 onward", "basedamage": "3.0/2.5/6.0", "shieldlag": "5/5/13", "shieldstun": "2/2/3", "whichhitbox": "--", "advantage": "-8/-7", "activeframes": "5/7/11\u201414"}, "up_air": {"hitbox": "hitboxes/greninja/GreninjaUAir.gif", "movename": "Up Air", "startup": "7/10/13/16/19/22", "totalframes": "41", "landinglag": "14", "notes": "Autocancels on frame 1-2 and 35 onward", "basedamage": "1.3/3.0", "shieldlag": "4/13", "shieldstun": "2/2", "whichhitbox": "Multi/Final", "advantage": "-12/-12", "activeframes": "7\u20148/10\u201411/13\u201414/16\u201417/19\u201420/22"}, "down_air": {"hitbox": "hitboxes/greninja/GreninjaDAir.gif", "movename": "Down Air", "startup": "17", "totalframes": "51", "landinglag": "30", "notes": "On-hit bounce animation takes 20 frames before you can act. Autocancels on frame 1-2 and 53 onward", "basedamage": "8.0", "shieldlag": "15", "shieldstun": "4", "whichhitbox": "Early/Late", "advantage": "-16", "activeframes": "17\u201419(20\u201445)"}, "neutral_b_(water_shuriken)": {"hitbox": "hitboxes/greninja/GreninjaWaterShuriken.png", "movename": "Neutral B (Water Shuriken)", "startup": "20\u201460", "totalframes": "** (see notes)", "landinglag": "--", "notes": "Hits on frames 6\u201441(rehit:4)/42 on release. Total Frames: 31 for any level of charge before max, 27 for max, 24 for any level of charge on aerial release, 20 for max charge aerial release.", "basedamage": "3.0\u201410.8, 1.0/9.0", "shieldlag": "5\u20148/4/11", "shieldstun": "2\u20144/2/4/10/11", "whichhitbox": "partial charge/full charge", "advantage": "-18 to -13", "activeframes": "20\u201435 \u2014 60\u201495"}, "side_b_(shadow_sneak)": {"hitbox": "hitboxes/greninja/GreninjaShadowSneakF.gif", "movename": "Side B (Shadow Sneak)", "startup": "24(+5)", "totalframes": "63", "landinglag": "--", "notes": "Startup is 24 from release. Must ready this move for at least five frames.", "basedamage": "10.0/12.0", "shieldlag": "10/12", "shieldstun": "10/11", "whichhitbox": "Front/Back Kick", "advantage": "-29/-28", "activeframes": "24\u201425"}, "up_b_(hydro_pump)": {"hitbox": "hitboxes/greninja/GreninjaHydroPump.gif", "movename": "Up B (Hydro Pump)", "startup": "19", "totalframes": "--", "landinglag": "32", "notes": "--", "basedamage": "2.0", "shieldlag": "8", "shieldstun": "2", "whichhitbox": "--", "advantage": "--", "activeframes": "**"}, "down_b_(substitute)": {"hitbox": "hitboxes/greninja/GreninjaSubstitute.gif", "movename": "Down B (Substitute)", "startup": "8 (Start of Counter)", "totalframes": "69", "landinglag": "--", "notes": "Invulnerable on frame 7. Counters on frame 8-34", "basedamage": "--", "shieldlag": "--", "shieldstun": "--", "whichhitbox": "--", "advantage": "--", "activeframes": "8\u201434 (counter)"}, "down_b,_attack_(substitute,_attack)": {"hitbox": "hitboxes/greninja/GreninjaSubstituteHitSide.gif", "movename": "Down B, Attack (Substitute, Attack)", "startup": "19", "totalframes": "63", "landinglag": "--", "notes": "Invulnerable on frame 1-33 in addition to 22 freeze frames.", "basedamage": "11.0/13.0", "shieldlag": "9/10", "shieldstun": "11/12", "whichhitbox": "Side/Up or Down", "advantage": "-33/-32", "activeframes": "19"}, "grab": {"hitbox": "hitboxes/greninja/GreninjaGrab.gif", "movename": "Grab", "startup": "10", "totalframes": "38", "landinglag": "--", "notes": "--", "basedamage": "--", "shieldlag": "9/10", "shieldstun": "11/12", "whichhitbox": "Side/Up or Down", "advantage": "-33/-32", "activeframes": "10\u201411"}, "dash_grab": {"hitbox": "hitboxes/greninja/GreninjaDashGrab.gif", "movename": "Dash Grab", "startup": "13", "totalframes": "46", "landinglag": "--", "notes": "--", "basedamage": "--", "shieldlag": "9/10", "shieldstun": "11/12", "whichhitbox": "Side/Up or Down", "advantage": "-33/-32", "activeframes": "13\u201414"}, "pivot_grab": {"hitbox": "hitboxes/greninja/GreninjaPivotGrab.gif", "movename": "Pivot Grab", "startup": "14", "totalframes": "41", "landinglag": "--", "notes": "--", "basedamage": "--", "shieldlag": "9/10", "shieldstun": "11/12", "whichhitbox": "Side/Up or Down", "advantage": "-33/-32", "activeframes": "14\u201415"}, "pummel": {"hitbox": "hitboxes/greninja/GreninjaPummel.gif", "movename": "Pummel", "startup": "2", "totalframes": "18", "landinglag": "Total frames includes 10 frames of hitlag.", "notes": "--", "basedamage": "1.0", "shieldlag": "9/10", "shieldstun": "11/12", "whichhitbox": "Side/Up or Down", "advantage": "-33/-32", "activeframes": "14\u201415"}, "forward_throw": {"hitbox": "hitboxes/greninja/GreninjaFThrow.gif", "movename": "Forward Throw", "startup": "15/16", "totalframes": "31", "landinglag": "--", "notes": "--", "basedamage": "3.5/4.5", "shieldlag": "9/10", "shieldstun": "11/12", "whichhitbox": "Side/Up or Down", "advantage": "-33/-32", "activeframes": "14\u201415"}, "backward_throw": {"hitbox": "hitboxes/greninja/GreninjaBThrow.gif", "movename": "Backward Throw", "startup": "18", "totalframes": "44", "landinglag": "--", "notes": "--", "basedamage": "9.0", "shieldlag": "9/10", "shieldstun": "11/12", "whichhitbox": "Side/Up or Down", "advantage": "-33/-32", "activeframes": "14\u201415"}, "up_throw": {"hitbox": "hitboxes/greninja/GreninjaUThrow.gif", "movename": "Up Throw", "startup": "16", "totalframes": "42", "landinglag": "--", "notes": "--", "basedamage": "5.0", "shieldlag": "9/10", "shieldstun": "11/12", "whichhitbox": "Side/Up or Down", "advantage": "-33/-32", "activeframes": "14\u201415"}, "down_throw": {"hitbox": "hitboxes/greninja/GreninjaDThrow.gif", "movename": "Down Throw", "startup": "16", "totalframes": "37", "landinglag": "--", "notes": "--", "basedamage": "5.0", "shieldlag": "9/10", "shieldstun": "11/12", "whichhitbox": "Side/Up or Down", "advantage": "-33/-32", "activeframes": "14\u201415"}, "spot_dodge": {"hitbox": "hitboxes/greninja/GreninjaDThrow.gif", "movename": "Spot Dodge", "startup": "16", "totalframes": "19/24", "landinglag": "--", "notes": "Intangible on frame 3-16.", "basedamage": "5.0", "shieldlag": "9/10", "shieldstun": "11/12", "whichhitbox": "Side/Up or Down", "advantage": "-33/-32", "activeframes": "14\u201415"}, "forward_roll": {"hitbox": "hitboxes/greninja/GreninjaDThrow.gif", "movename": "Forward Roll", "startup": "16", "totalframes": "28", "landinglag": "--", "notes": "Intangible on frame 4-14.", "basedamage": "5.0", "shieldlag": "9/10", "shieldstun": "11/12", "whichhitbox": "Side/Up or Down", "advantage": "-33/-32", "activeframes": "14\u201415"}, "backward_roll": {"hitbox": "hitboxes/greninja/GreninjaDThrow.gif", "movename": "Backward Roll", "startup": "16", "totalframes": "33", "landinglag": "--", "notes": "Intangible on frame 4-15.", "basedamage": "5.0", "shieldlag": "9/10", "shieldstun": "11/12", "whichhitbox": "Side/Up or Down", "advantage": "-33/-32", "activeframes": "14\u201415"}, "neutral_air_dodge": {"hitbox": "hitboxes/greninja/GreninjaDThrow.gif", "movename": "Neutral Air Dodge", "startup": "16", "totalframes": "41", "landinglag": "10", "notes": "Intangible on frame 2-27.", "basedamage": "5.0", "shieldlag": "9/10", "shieldstun": "11/12", "whichhitbox": "Side/Up or Down", "advantage": "-33/-32", "activeframes": "14\u201415"}, "air_dodge,_down": {"hitbox": "hitboxes/greninja/GreninjaDThrow.gif", "movename": "Air Dodge, Down", "startup": "16", "totalframes": "60", "landinglag": "11-19", "notes": "Intangible on frame 2-19.", "basedamage": "5.0", "shieldlag": "9/10", "shieldstun": "11/12", "whichhitbox": "Side/Up or Down", "advantage": "-33/-32", "activeframes": "14\u201415"}, "air_dodge,_diagonally_down": {"hitbox": "hitboxes/greninja/GreninjaDThrow.gif", "movename": "Air Dodge, Diagonally Down", "startup": "16", "totalframes": "67", "landinglag": "11-19", "notes": "Intangible on frame 2-19.", "basedamage": "5.0", "shieldlag": "9/10", "shieldstun": "11/12", "whichhitbox": "Side/Up or Down", "advantage": "-33/-32", "activeframes": "14\u201415"}, "air_dodge,_left/right": {"hitbox": "hitboxes/greninja/GreninjaDThrow.gif", "movename": "Air Dodge, Left/Right", "startup": "16", "totalframes": "71", "landinglag": "11-19", "notes": "Intangible on frame 2-19.", "basedamage": "5.0", "shieldlag": "9/10", "shieldstun": "11/12", "whichhitbox": "Side/Up or Down", "advantage": "-33/-32", "activeframes": "14\u201415"}, "air_dodge,_diagonally_up": {"hitbox": "hitboxes/greninja/GreninjaDThrow.gif", "movename": "Air Dodge, Diagonally Up", "startup": "16", "totalframes": "78", "landinglag": "11-19", "notes": "Intangible on frame 2-19.", "basedamage": "5.0", "shieldlag": "9/10", "shieldstun": "11/12", "whichhitbox": "Side/Up or Down", "advantage": "-33/-32", "activeframes": "14\u201415"}, "air_dodge,_up": {"hitbox": "hitboxes/greninja/GreninjaDThrow.gif", "movename": "Air Dodge, Up", "startup": "16", "totalframes": "85", "landinglag": "11-19", "notes": "Intangible on frame 2-19.", "basedamage": "5.0", "shieldlag": "9/10", "shieldstun": "11/12", "whichhitbox": "Side/Up or Down", "advantage": "-33/-32", "activeframes": "14\u201415"}, "stats": {"hitbox": "hitboxes/greninja/GreninjaDThrow.gif", "movename": "Stats", "startup": "16", "totalframes": "85", "landinglag": "11-19", "notes": "Intangible on frame 2-19.", "basedamage": "5.0", "shieldlag": "9/10", "shieldstun": "11/12", "whichhitbox": "Side/Up or Down", "advantage": "-33/-32", "activeframes": "14\u201415", "oos1": "Out of Shield, Back Air \u2014 8 frames", "oos2": "Out of Shield, Up Air \u2014 10 frames", "oos3": "Out of Shield, Up Smash \u2014 12 frames"}, "ledge_grab": {"hitbox": "ledgegrabs/Greninja Ledgegrab 1 (Normal).png", "movename": "Ledge Grab", "startup": "16", "totalframes": "85", "landinglag": "11-19", "notes": "Intangible on frame 2-19.", "basedamage": "5.0", "shieldlag": "9/10", "shieldstun": "11/12", "whichhitbox": "Side/Up or Down", "advantage": "-33/-32", "activeframes": "14\u201415", "oos1": "Out of Shield, Back Air \u2014 8 frames", "oos2": "Out of Shield, Up Air \u2014 10 frames", "oos3": "Out of Shield, Up Smash \u2014 12 frames"}, "ledge_hang": {"hitbox": "ledgehangs/Greninja Ledgehang.gif", "movename": "Ledge Hang", "startup": "16", "totalframes": "85", "landinglag": "11-19", "notes": "Intangible on frame 2-19.", "basedamage": "5.0", "shieldlag": "9/10", "shieldstun": "11/12", "whichhitbox": "Side/Up or Down", "advantage": "-33/-32", "activeframes": "14\u201415", "oos1": "Out of Shield, Back Air \u2014 8 frames", "oos2": "Out of Shield, Up Air \u2014 10 frames", "oos3": "Out of Shield, Up Smash \u2014 12 frames"}, "getup_attacks": {"hitbox": "hitboxes/greninja/greninjaGetupAttackU.gif", "movename": "Getup Attacks", "startup": "16", "totalframes": "85", "landinglag": "11-19", "notes": "Intangible on frame 2-19.", "basedamage": "5.0", "shieldlag": "9/10", "shieldstun": "11/12", "whichhitbox": "Side/Up or Down", "advantage": "-33/-32", "activeframes": "14\u201415", "oos1": "Out of Shield, Back Air \u2014 8 frames", "oos2": "Out of Shield, Up Air \u2014 10 frames", "oos3": "Out of Shield, Up Smash \u2014 12 frames"}}}