{"url": "/wario", "date": "2022-09-19 15:01:16.264033", "moves": {"jab": {"hitbox": "hitboxes/wario/WarioJab1.gif", "movename": "Jab", "startup": "8", "totalframes": "27", "landinglag": "--", "notes": "Transitions to Jab 2 as early as frame 10.", "basedamage": "4.0", "shieldlag": "9", "shieldstun": "5", "whichhitbox": "--", "advantage": "-16", "activeframes": "8\u20149"}, "jab_2": {"hitbox": "hitboxes/wario/WarioJab2.gif", "movename": "Jab 2", "startup": "4", "totalframes": "29", "landinglag": "--", "notes": "--", "basedamage": "5.0", "shieldlag": "12", "shieldstun": "6", "whichhitbox": "--", "advantage": "-23", "activeframes": "4\u20145"}, "forward_tilt": {"hitbox": "hitboxes/wario/WarioFTilt.gif", "movename": "Forward Tilt", "startup": "12", "totalframes": "39", "landinglag": "--", "notes": "--", "basedamage": "13.0/10.0", "shieldlag": "9", "shieldstun": "12", "whichhitbox": "Far/Close", "advantage": "-15", "activeframes": "12\u201415"}, "up_tilt": {"hitbox": "hitboxes/wario/WarioUTilt.gif", "movename": "Up Tilt", "startup": "8", "totalframes": "27", "landinglag": "--", "notes": "--", "basedamage": "6.0/5.0", "shieldlag": "6", "shieldstun": "6", "whichhitbox": "Early/Late", "advantage": "-13", "activeframes": "8\u201410/11\u201415"}, "down_tilt": {"hitbox": "hitboxes/wario/WarioDTilt.gif", "movename": "Down Tilt", "startup": "5", "totalframes": "17", "landinglag": "--", "notes": "--", "basedamage": "4.0", "shieldlag": "5", "shieldstun": "5", "whichhitbox": "--", "advantage": "-7", "activeframes": "5"}, "dash_attack": {"hitbox": "hitboxes/wario/WarioDashAttack.gif", "movename": "Dash Attack", "startup": "5", "totalframes": "48", "landinglag": "--", "notes": "--", "basedamage": "11.0/5.0", "shieldlag": "8/6", "shieldstun": "10/6", "whichhitbox": "Early/Late", "advantage": "-33", "activeframes": "5\u20148/9\u201423"}, "forward_smash": {"hitbox": "hitboxes/wario/WarioFSmash.gif", "movename": "Forward Smash", "startup": "18", "totalframes": "65", "landinglag": "--", "notes": "Charge hold is frame 4", "basedamage": "20.0", "shieldlag": "12", "shieldstun": "13", "whichhitbox": "--", "advantage": "-34", "activeframes": "18\u201419"}, "up_smash": {"hitbox": "hitboxes/wario/WarioUSmash.gif", "movename": "Up Smash", "startup": "11", "totalframes": "57", "landinglag": "--", "notes": "Head intangibility on frame 8-14. Charge hold is frame 4", "basedamage": "17.0/13.0", "shieldlag": "11/9", "shieldstun": "11/9", "whichhitbox": "Close/Far", "advantage": "-35/-37", "activeframes": "11\u201412/13"}, "down_smash": {"hitbox": "hitboxes/wario/WarioDSmash.gif", "movename": "Down Smash", "startup": "8", "totalframes": "61", "landinglag": "--", "notes": "Charge hold is frame 2", "basedamage": "13.0/10.0/5.0", "shieldlag": "9", "shieldstun": "9", "whichhitbox": "Early/Late/Later", "advantage": "-44", "activeframes": "8\u201417/18\u201427/28\u201436"}, "neutral_air": {"hitbox": "hitboxes/wario/WarioNAir.gif", "movename": "Neutral Air", "startup": "4/20", "totalframes": "45", "landinglag": "7", "notes": "Autocancels on frame 1-3 and 43 onward", "basedamage": "6.0/3.0/6.0/4.0/5.0", "shieldlag": "6/6", "shieldstun": "3/3", "whichhitbox": "Early Hit 1/Late Hit 1 Hands/Late Hit 1 Body/Early Hit 2/Late Hit 2", "advantage": "-4/-4", "activeframes": "4\u201412(13\u201417)/20\u201426(27\u201442)"}, "forward_air": {"hitbox": "hitboxes/wario/WarioFAir.gif", "movename": "Forward Air", "startup": "5", "totalframes": "37", "landinglag": "10", "notes": "Autocancels on frame 1-4 and 27 onward", "basedamage": "7.0 / 4.5", "shieldlag": "7/5", "shieldstun": "3/3", "whichhitbox": "Early/Late", "advantage": "-7/-7", "activeframes": "5\u20146/7\u201417"}, "back_air": {"hitbox": "hitboxes/wario/WarioBAir.gif", "movename": "Back Air", "startup": "9", "totalframes": "49", "landinglag": "16", "notes": "Autocancels on frame 1-4 and 34 onward", "basedamage": "12.0", "shieldlag": "9", "shieldstun": "5", "whichhitbox": "--", "advantage": "-11", "activeframes": "9\u201411"}, "up_air": {"hitbox": "hitboxes/wario/WarioUAir.gif", "movename": "Up Air", "startup": "8", "totalframes": "46", "landinglag": "7", "notes": "Autocancels on frame 1-3 and 37 onward", "basedamage": "13.0", "shieldlag": "9", "shieldstun": "5", "whichhitbox": "--", "advantage": "-2", "activeframes": "8\u20149"}, "down_air": {"hitbox": "hitboxes/wario/WarioDAir.gif", "movename": "Down Air", "startup": "9/11/13/15/17/19/21", "totalframes": "47", "landinglag": "18", "notes": "Autocancels on frame 1-2 and 42 onward", "basedamage": "1.3/4.0", "shieldlag": "4/11", "shieldstun": "2/3", "whichhitbox": "Multi/Final", "advantage": "-16/-15", "activeframes": "9/11/13/15/17/19/21"}, "neutral_b_(chomp)": {"hitbox": "hitboxes/wario/WarioChomp.gif", "movename": "Neutral B (Chomp)", "startup": "8 (11 Grab Release)", "totalframes": "41 (19 Grab Release)", "landinglag": "--", "notes": "25 endlag from release of the button. Can eat projectiles on frame 9\u2014. With the exception of Bike being eaten on frame 2. Animation for eating a projectile is 25 frames. 55 for the Bike.", "basedamage": "--", "shieldlag": "--", "shieldstun": "--", "whichhitbox": "--", "advantage": "--", "activeframes": "8\u201416 (Can hold: 8\u201464)"}, "side_b_(wario_bike)": {"hitbox": "hitboxes/wario/WarioBikeDrive.gif", "movename": "Side B (Wario Bike)", "startup": "20/24", "totalframes": "--", "landinglag": "--", "notes": "Startup is 24 if mounting a bike laying on the ground. Frame 20 is the earliest you can jump, turnaround, wheelie. Wario seems to suffer more shieldlag than the defender on any hit.", "basedamage": "0.6\u201411.4", "shieldlag": "4-8, 6-13(Wario)", "shieldstun": "2\u20144", "whichhitbox": "--", "advantage": "**", "activeframes": "20\u2014**"}, "wario_bike,_wheelie": {"hitbox": "hitboxes/wario/WarioBikeWheelie.gif", "movename": "Wario Bike, Wheelie", "startup": "4/54", "totalframes": "64", "landinglag": "--", "notes": "Bike armor on frame 10. Jump animation takes 28 frames.", "basedamage": "5.0/13.0", "shieldlag": "8/9, 11/14(Wario)", "shieldstun": "3/5", "whichhitbox": "--", "advantage": "-60/-10", "activeframes": "**"}, "wario_bike,_turnaround": {"hitbox": "hitboxes/wario/WarioBikeTurn.gif", "movename": "Wario Bike, Turnaround", "startup": "6", "totalframes": "45", "landinglag": "--", "notes": "Looking for Bike animation takes 39 frames", "basedamage": "7.0", "shieldlag": "8, 12(Wario)", "shieldstun": "3", "whichhitbox": "--", "advantage": "-40", "activeframes": "**"}, "bike_(thrown_/_item)": {"hitbox": "hitboxes/wario/WarioBikeThrown.png", "movename": "Bike (Thrown / Item)", "startup": "--", "totalframes": "--", "landinglag": "--", "notes": "--", "basedamage": "--", "shieldlag": "--", "shieldstun": "--", "whichhitbox": "--", "advantage": "--", "activeframes": "--"}, "up_b_(corkscrew)": {"hitbox": "hitboxes/wario/WarioCorkscrew.gif", "movename": "Up B (Corkscrew)", "startup": "6/8/12/16/20/29", "totalframes": "--", "landinglag": "20", "notes": "--", "basedamage": "5.0/1.0/4.0", "shieldlag": "6/4/11", "shieldstun": "-/2/5", "whichhitbox": "First/Multi/Final", "advantage": "**", "activeframes": "6\u20147/8\u201411/12\u201415/16\u201419/20\u201423/29\u201430"}, "down_b_(wario_waft)": {"hitbox": "hitboxes/wario/WarioWarioWaftToot.gif", "movename": "Down B (Wario Waft)", "startup": "16, 10, 8, 12", "totalframes": "79, 64, 54, 63", "landinglag": "--", "notes": "Full Waft has armor on frames 4\u201413.", "basedamage": "0.0, 12.0+, 20.0+, 27.0/20.0", "shieldlag": "--, 10, 13, 19/12", "shieldstun": "--, 13, 20, 23/18", "whichhitbox": "Stage 1, Stage 2, Stage 3, Final Stage Early/Late", "advantage": "--, -41, -24, -28", "activeframes": "16\u201418, 10\u201411, 8\u201411, 12\u201413/14\u201429"}, "grab": {"hitbox": "hitboxes/wario/WarioGrab.gif", "movename": "Grab", "startup": "8", "totalframes": "35", "landinglag": "--", "notes": "--", "basedamage": "--", "shieldlag": "--, 10, 13, 19/12", "shieldstun": "--, 13, 20, 23/18", "whichhitbox": "Stage 1, Stage 2, Stage 3, Final Stage Early/Late", "advantage": "--, -41, -24, -28", "activeframes": "8\u201410"}, "dash_grab": {"hitbox": "hitboxes/wario/WarioDashGrab.gif", "movename": "Dash Grab", "startup": "11", "totalframes": "43", "landinglag": "--", "notes": "--", "basedamage": "--", "shieldlag": "--, 10, 13, 19/12", "shieldstun": "--, 13, 20, 23/18", "whichhitbox": "Stage 1, Stage 2, Stage 3, Final Stage Early/Late", "advantage": "--, -41, -24, -28", "activeframes": "11\u201413"}, "pivot_grab": {"hitbox": "hitboxes/wario/WarioPivotGrab.gif", "movename": "Pivot Grab", "startup": "12", "totalframes": "38", "landinglag": "--", "notes": "--", "basedamage": "--", "shieldlag": "--, 10, 13, 19/12", "shieldstun": "--, 13, 20, 23/18", "whichhitbox": "Stage 1, Stage 2, Stage 3, Final Stage Early/Late", "advantage": "--, -41, -24, -28", "activeframes": "12\u201414"}, "pummel": {"hitbox": "hitboxes/wario/WarioPummel.gif", "movename": "Pummel", "startup": "2", "totalframes": "21", "landinglag": "Total frames includes 14 frames of hitlag.", "notes": "--", "basedamage": "1.6", "shieldlag": "--, 10, 13, 19/12", "shieldstun": "--, 13, 20, 23/18", "whichhitbox": "Stage 1, Stage 2, Stage 3, Final Stage Early/Late", "advantage": "--, -41, -24, -28", "activeframes": "12\u201414"}, "forward_throw": {"hitbox": "hitboxes/wario/WarioFThrow.gif", "movename": "Forward Throw", "startup": "20/21", "totalframes": "54", "landinglag": "--", "notes": "--", "basedamage": "4.0/8.0", "shieldlag": "--, 10, 13, 19/12", "shieldstun": "--, 13, 20, 23/18", "whichhitbox": "Stage 1, Stage 2, Stage 3, Final Stage Early/Late", "advantage": "--, -41, -24, -28", "activeframes": "12\u201414"}, "backward_throw": {"hitbox": "hitboxes/wario/WarioBThrow.gif", "movename": "Backward Throw", "startup": "48", "totalframes": "69", "landinglag": "--", "notes": "--", "basedamage": "7.0", "shieldlag": "--, 10, 13, 19/12", "shieldstun": "--, 13, 20, 23/18", "whichhitbox": "Stage 1, Stage 2, Stage 3, Final Stage Early/Late", "advantage": "--, -41, -24, -28", "activeframes": "12\u201414"}, "up_throw": {"hitbox": "hitboxes/wario/WarioUThrow.gif", "movename": "Up Throw", "startup": "24/25", "totalframes": "43", "landinglag": "--", "notes": "--", "basedamage": "4.0/4.0", "shieldlag": "--, 10, 13, 19/12", "shieldstun": "--, 13, 20, 23/18", "whichhitbox": "Stage 1, Stage 2, Stage 3, Final Stage Early/Late", "advantage": "--, -41, -24, -28", "activeframes": "12\u201414"}, "down_throw": {"hitbox": "hitboxes/wario/WarioDThrow.gif", "movename": "Down Throw", "startup": "22/30", "totalframes": "54", "landinglag": "--", "notes": "--", "basedamage": "4.0/7.0", "shieldlag": "--, 10, 13, 19/12", "shieldstun": "--, 13, 20, 23/18", "whichhitbox": "Stage 1, Stage 2, Stage 3, Final Stage Early/Late", "advantage": "--, -41, -24, -28", "activeframes": "12\u201414"}, "spot_dodge": {"hitbox": "hitboxes/wario/WarioDThrow.gif", "movename": "Spot Dodge", "startup": "22/30", "totalframes": "21/26", "landinglag": "--", "notes": "Intangible on frame 3-17", "basedamage": "4.0/7.0", "shieldlag": "--, 10, 13, 19/12", "shieldstun": "--, 13, 20, 23/18", "whichhitbox": "Stage 1, Stage 2, Stage 3, Final Stage Early/Late", "advantage": "--, -41, -24, -28", "activeframes": "12\u201414"}, "forward_roll": {"hitbox": "hitboxes/wario/WarioDThrow.gif", "movename": "Forward Roll", "startup": "22/30", "totalframes": "30", "landinglag": "--", "notes": "Intangible on frame 4-15", "basedamage": "4.0/7.0", "shieldlag": "--, 10, 13, 19/12", "shieldstun": "--, 13, 20, 23/18", "whichhitbox": "Stage 1, Stage 2, Stage 3, Final Stage Early/Late", "advantage": "--, -41, -24, -28", "activeframes": "12\u201414"}, "backward_roll": {"hitbox": "hitboxes/wario/WarioDThrow.gif", "movename": "Backward Roll", "startup": "22/30", "totalframes": "35", "landinglag": "--", "notes": "Intangible on frame 5-16", "basedamage": "4.0/7.0", "shieldlag": "--, 10, 13, 19/12", "shieldstun": "--, 13, 20, 23/18", "whichhitbox": "Stage 1, Stage 2, Stage 3, Final Stage Early/Late", "advantage": "--, -41, -24, -28", "activeframes": "12\u201414"}, "neutral_air_dodge": {"hitbox": "hitboxes/wario/WarioDThrow.gif", "movename": "Neutral Air Dodge", "startup": "22/30", "totalframes": "50", "landinglag": "10", "notes": "Intangible on frame 3-29", "basedamage": "4.0/7.0", "shieldlag": "--, 10, 13, 19/12", "shieldstun": "--, 13, 20, 23/18", "whichhitbox": "Stage 1, Stage 2, Stage 3, Final Stage Early/Late", "advantage": "--, -41, -24, -28", "activeframes": "12\u201414"}, "air_dodge,_down": {"hitbox": "hitboxes/wario/WarioDThrow.gif", "movename": "Air Dodge, Down", "startup": "22/30", "totalframes": "66", "landinglag": "11-19", "notes": "Intangible on frame 3-21", "basedamage": "4.0/7.0", "shieldlag": "--, 10, 13, 19/12", "shieldstun": "--, 13, 20, 23/18", "whichhitbox": "Stage 1, Stage 2, Stage 3, Final Stage Early/Late", "advantage": "--, -41, -24, -28", "activeframes": "12\u201414"}, "air_dodge,_diagonally_down": {"hitbox": "hitboxes/wario/WarioDThrow.gif", "movename": "Air Dodge, Diagonally Down", "startup": "22/30", "totalframes": "75", "landinglag": "11-19", "notes": "Intangible on frame 3-21", "basedamage": "4.0/7.0", "shieldlag": "--, 10, 13, 19/12", "shieldstun": "--, 13, 20, 23/18", "whichhitbox": "Stage 1, Stage 2, Stage 3, Final Stage Early/Late", "advantage": "--, -41, -24, -28", "activeframes": "12\u201414"}, "air_dodge,_left/right": {"hitbox": "hitboxes/wario/WarioDThrow.gif", "movename": "Air Dodge, Left/Right", "startup": "22/30", "totalframes": "82", "landinglag": "11-19", "notes": "Intangible on frame 3-21", "basedamage": "4.0/7.0", "shieldlag": "--, 10, 13, 19/12", "shieldstun": "--, 13, 20, 23/18", "whichhitbox": "Stage 1, Stage 2, Stage 3, Final Stage Early/Late", "advantage": "--, -41, -24, -28", "activeframes": "12\u201414"}, "air_dodge,_diagonally_up": {"hitbox": "hitboxes/wario/WarioDThrow.gif", "movename": "Air Dodge, Diagonally Up", "startup": "22/30", "totalframes": "97", "landinglag": "11-19", "notes": "Intangible on frame 3-21", "basedamage": "4.0/7.0", "shieldlag": "--, 10, 13, 19/12", "shieldstun": "--, 13, 20, 23/18", "whichhitbox": "Stage 1, Stage 2, Stage 3, Final Stage Early/Late", "advantage": "--, -41, -24, -28", "activeframes": "12\u201414"}, "air_dodge,_up": {"hitbox": "hitboxes/wario/WarioDThrow.gif", "movename": "Air Dodge, Up", "startup": "22/30", "totalframes": "104", "landinglag": "11-19", "notes": "Intangible on frame 3-21", "basedamage": "4.0/7.0", "shieldlag": "--, 10, 13, 19/12", "shieldstun": "--, 13, 20, 23/18", "whichhitbox": "Stage 1, Stage 2, Stage 3, Final Stage Early/Late", "advantage": "--, -41, -24, -28", "activeframes": "12\u201414"}, "stats": {"hitbox": "hitboxes/wario/WarioDThrow.gif", "movename": "Stats", "startup": "22/30", "totalframes": "104", "landinglag": "11-19", "notes": "Intangible on frame 3-21", "basedamage": "4.0/7.0", "shieldlag": "--, 10, 13, 19/12", "shieldstun": "--, 13, 20, 23/18", "whichhitbox": "Stage 1, Stage 2, Stage 3, Final Stage Early/Late", "advantage": "--, -41, -24, -28", "activeframes": "12\u201414", "oos1": "Out of Shield, Up B \u2014 6 frames", "oos2": "Out of Shield, Neutral Air \u2014 7 frames", "oos3": "Out of Shield, Forward Air \u2014 8 frames"}, "ledge_grab": {"hitbox": "ledgegrabs/Wario Ledgegrab 1.png", "movename": "Ledge Grab", "startup": "22/30", "totalframes": "104", "landinglag": "11-19", "notes": "Intangible on frame 3-21", "basedamage": "4.0/7.0", "shieldlag": "--, 10, 13, 19/12", "shieldstun": "--, 13, 20, 23/18", "whichhitbox": "Stage 1, Stage 2, Stage 3, Final Stage Early/Late", "advantage": "--, -41, -24, -28", "activeframes": "12\u201414", "oos1": "Out of Shield, Up B \u2014 6 frames", "oos2": "Out of Shield, Neutral Air \u2014 7 frames", "oos3": "Out of Shield, Forward Air \u2014 8 frames"}, "ledge_hang": {"hitbox": "ledgehangs/Wario Ledgehang.gif", "movename": "Ledge Hang", "startup": "22/30", "totalframes": "104", "landinglag": "11-19", "notes": "Intangible on frame 3-21", "basedamage": "4.0/7.0", "shieldlag": "--, 10, 13, 19/12", "shieldstun": "--, 13, 20, 23/18", "whichhitbox": "Stage 1, Stage 2, Stage 3, Final Stage Early/Late", "advantage": "--, -41, -24, -28", "activeframes": "12\u201414", "oos1": "Out of Shield, Up B \u2014 6 frames", "oos2": "Out of Shield, Neutral Air \u2014 7 frames", "oos3": "Out of Shield, Forward Air \u2014 8 frames"}, "getup_attacks": {"hitbox": "hitboxes/wario/warioGetupAttackU.gif", "movename": "Getup Attacks", "startup": "22/30", "totalframes": "104", "landinglag": "11-19", "notes": "Intangible on frame 3-21", "basedamage": "4.0/7.0", "shieldlag": "--, 10, 13, 19/12", "shieldstun": "--, 13, 20, 23/18", "whichhitbox": "Stage 1, Stage 2, Stage 3, Final Stage Early/Late", "advantage": "--, -41, -24, -28", "activeframes": "12\u201414", "oos1": "Out of Shield, Up B \u2014 6 frames", "oos2": "Out of Shield, Neutral Air \u2014 7 frames", "oos3": "Out of Shield, Forward Air \u2014 8 frames"}}}